{
    "@class": "com.kony.gen.viz.model.component.KVizLabel",
    "DNDConfig": null,
    "__parentReadjusting__": false,
    "_height_": {
        "type": "ref",
        "value": "preferred"
    },
    "_margin_": [
        1,
        1,
        1,
        1
    ],
    "_padding_": [
        0,
        0,
        0,
        0
    ],
    "_skin_": "s034b71218f4414ab1dd7bb7bf61c06e",
    "_text_": "",
    "_width_": {
        "type": "ref",
        "value": "preferred"
    },
    "_wrapping_": 2,
    "android": {
        "textStyle": {
            "letterSpacing": 0,
            "strikeThrough": false
        }
    },
    "canUpdateUI": true,
    "centerx": {
        "type": "string",
        "value": "50%"
    },
    "centery": {
        "type": "string",
        "value": "50%"
    },
    "containerweight": 100,
    "contentalignment": 4,
    "id": "lblHeader",
    "info": null,
    "ipad": {
        "psp": {
            "wrapping": 2
        }
    },
    "isvisible": true,
    "kuid": "a4ecdda73c774826818dea513f089e8f",
    "name": "kony.ui.Label",
    "parent": "FlexContainer0g7957b999fe54f",
    "pf": "settingpage",
    "texti18n": "settingpagelblHeader",
    "tooltip": "",
    "wType": "Label",
    "zindex": 1
}