{
    "DNDConfig": null,
    "__parentReadjusting__": false,
    "_height_": {
        "type": "string",
        "value": "45dp"
    },
    "_left_": {
        "type": "string",
        "value": "0dp"
    },
    "_margin_": [
        0,
        0,
        0,
        0
    ],
    "_orientation_": 6,
    "_padding_": [
        0,
        0,
        0,
        0
    ],
    "_percent_": true,
    "_skin_": "s15bafe233aa4de199a471d538aaf7ce",
    "_top_": {
        "type": "string",
        "value": "0dp"
    },
    "_width_": {
        "type": "string",
        "value": "45dp"
    },
    "allboxes": [],
    "autogrowmode": 0,
    "canUpdateUI": true,
    "centery": {
        "type": "string",
        "value": "50%"
    },
    "children": [
        "Image0b68eae06afd747"
    ],
    "clipbounds": true,
    "containerweight": 100,
    "enablescrolling": true,
    "id": "flxBackBtn",
    "info": null,
    "isvisible": true,
    "kuid": "a05559165a5847a3bd85342ce1c7a183",
    "layouttype": 2,
    "name": "kony.ui.FlexContainer",
    "parent": "FlexContainer0g8c7199caee440",
    "pf": "userwidgetmodel",
    "snapgridsize": 10,
    "snaptogrid": true,
    "wType": "FlexContainer",
    "widgetalignment": 1,
    "zindex": 1
}