{
    "DNDConfig": null,
    "__parentReadjusting__": false,
    "_height_": {
        "type": "string",
        "value": "1dp"
    },
    "_left_": {
        "type": "string",
        "value": "0dp"
    },
    "_margin_": [
        0,
        0,
        0,
        0
    ],
    "_orientation_": 6,
    "_padding_": [
        0,
        0,
        0,
        0
    ],
    "_percent_": true,
    "_skin_": "s4c42ee81c644294881f7a091d1189c5",
    "_top_": {
        "type": "string",
        "value": "0dp"
    },
    "_width_": {
        "type": "string",
        "value": "100%"
    },
    "allboxes": [],
    "autogrowmode": 0,
    "canUpdateUI": true,
    "children": [],
    "clipbounds": true,
    "containerweight": 100,
    "enablescrolling": true,
    "id": "FlexContainer0jfed6f22741740",
    "info": null,
    "isvisible": true,
    "kuid": "c3d9773d828a4cf384a7ee3dc636737a",
    "layouttype": 2,
    "name": "kony.ui.FlexContainer",
    "parent": "FlexContainer0deb7aec3405e43",
    "pf": "userwidgetmodel",
    "snapgridsize": 10,
    "snaptogrid": true,
    "wType": "FlexContainer",
    "widgetalignment": 1,
    "zindex": 1
}