{
    "@class": "com.kony.gen.viz.model.component.KVizButton",
    "DNDConfig": null,
    "__parentReadjusting__": false,
    "_height_": {
        "type": "string",
        "value": "23%"
    },
    "_left_": {
        "type": "string",
        "value": "0dp"
    },
    "_margin_": [
        6,
        6,
        6,
        6
    ],
    "_padding_": [
        0,
        0,
        0,
        0
    ],
    "_skin_": "sb76db624fa84ca5a93681a561cc93f4",
    "_text_": "YES",
    "_top_": {
        "type": "string",
        "value": "0dp"
    },
    "_width_": {
        "type": "string",
        "value": "30%"
    },
    "canUpdateUI": true,
    "centerx": {
        "type": "string",
        "value": "29.06%"
    },
    "centery": {
        "type": "string",
        "value": "70.89%"
    },
    "containerweight": 100,
    "contentalignment": 5,
    "disabledSkins": {},
    "displaytext": true,
    "focusskin": "sb76db624fa84ca5a93681a561cc93f4",
    "id": "btnLogoutYes",
    "info": null,
    "isvisible": true,
    "kuid": "eaea33e520b548d8b9e270070dbdd615",
    "name": "kony.ui.Button",
    "parent": "flxLogOutBox",
    "pf": "userwidgetmodel",
    "texti18n": "YesLabel",
    "wType": "Button",
    "zindex": 3
}