{
    "DNDConfig": null,
    "__markedForDelete__": true,
    "__parentReadjusting__": false,
    "_height_": {
        "type": "string",
        "value": "40dp"
    },
    "_left_": {
        "type": "string",
        "value": "0dp"
    },
    "_margin_": [
        0,
        0,
        0,
        0
    ],
    "_orientation_": 6,
    "_padding_": [
        0,
        0,
        0,
        0
    ],
    "_percent_": true,
    "_skin_": "s5e9a3f816e848878969462492d48489",
    "_top_": {
        "type": "string",
        "value": "0dp"
    },
    "_width_": {
        "type": "string",
        "value": "100%"
    },
    "allboxes": [],
    "autogrowmode": 0,
    "canUpdateUI": true,
    "children": [
        "flxStoreLocatorRecentSearchTitle",
        "flxStoreLocatorRecentSearchDivider"
    ],
    "clipbounds": true,
    "containerweight": 100,
    "enablescrolling": true,
    "id": "flxStoreLocatorRecentSearchHeader",
    "info": null,
    "isvisible": true,
    "kuid": "c9d43d04a8554e18bc30f8af5a57cd77",
    "layouttype": 2,
    "name": "kony.ui.FlexContainer",
    "parent": "flxRecentSearch",
    "pf": "storelocatorpage",
    "snapgridsize": 10,
    "snaptogrid": true,
    "wType": "FlexContainer",
    "widgetalignment": 1,
    "zindex": 1
}