{
    "DNDConfig": null,
    "__parentReadjusting__": false,
    "_height_": {
        "type": "string",
        "value": "100%"
    },
    "_left_": {
        "type": "string",
        "value": "0dp"
    },
    "_margin_": [
        0,
        0,
        0,
        0
    ],
    "_orientation_": 6,
    "_padding_": [
        0,
        0,
        0,
        0
    ],
    "_percent_": true,
    "_skin_": "s7c57f38462e41ca9d2c1d23be763f8e",
    "_top_": {
        "type": "string",
        "value": "0dp"
    },
    "_width_": {
        "type": "string",
        "value": "100%"
    },
    "allboxes": [],
    "autogrowmode": 0,
    "canUpdateUI": true,
    "children": [
        "CopyAccordionActiveIcon0g11e912d02e44b",
        "CopyFlexContainer0ca06b8511fc946",
        "CopyAccordionActiveChevron0fb03fe95824842"
    ],
    "clipbounds": true,
    "containerweight": 100,
    "enablescrolling": true,
    "id": "AccordionActive6",
    "info": null,
    "isvisible": false,
    "kuid": "945e259bdf274048af22c4b3041c55b6",
    "layouttype": 2,
    "name": "kony.ui.FlexContainer",
    "parent": "AccordionButton6",
    "pf": "userwidgetmodel",
    "snapgridsize": 10,
    "snaptogrid": true,
    "wType": "FlexContainer",
    "widgetalignment": 1,
    "zindex": 1
}