{
    "DNDConfig": null,
    "__parentReadjusting__": false,
    "_height_": {
        "type": "string",
        "value": "100%"
    },
    "_left_": {
        "type": "string",
        "value": "0dp"
    },
    "_margin_": [
        0,
        0,
        0,
        0
    ],
    "_orientation_": 6,
    "_padding_": [
        0,
        0,
        0,
        0
    ],
    "_percent_": true,
    "_skin_": "s7c57f38462e41ca9d2c1d23be763f8e",
    "_top_": {
        "type": "string",
        "value": "0dp"
    },
    "_width_": {
        "type": "string",
        "value": "100%"
    },
    "allboxes": [],
    "autogrowmode": 0,
    "canUpdateUI": true,
    "children": [
        "CopyFlexContainer0e0e1af1d491f49",
        "CopyFlexContainer0ed6109bbefd14e",
        "CopyFlexContainer0i246f1d7e09847"
    ],
    "clipbounds": true,
    "containerweight": 100,
    "enablescrolling": true,
    "id": "CopyFlexContainer0jbf6763652cc4f",
    "info": null,
    "isvisible": true,
    "kuid": "5eb285148a624a0a8d986377c1ee4e30",
    "layouttype": 2,
    "name": "kony.ui.FlexContainer",
    "parent": "flxManufacturing",
    "pf": "userwidgetmodel",
    "snapgridsize": 10,
    "snaptogrid": true,
    "wType": "FlexContainer",
    "widgetalignment": 1,
    "zindex": 1
}