{
    "AS_Button_hcbe0956be38469eaa9fc6270b6c3a95": {
        "id": "AS_Button_hcbe0956be38469eaa9fc6270b6c3a95",
        "type": "ACTION_SEQUENCE",
        "params": [{
            "datatype": "collection",
            "name": "eventobject"
        }],
        "contextObj": {
            "name": "incomeSimulatorLOS",
            "type": "forms",
            "platform": "",
            "KUID": "b93cd434e25d4cf9a8c8b064fdd5a65e"
        },
        "language": "js",
        "actions": [{
            "id": "ADD_SNIPPET__c6e727d383d44d758960240c3b09bbfd",
            "type": "ADD_SNIPPET",
            "codeSnippet": "this.showPopup(eventobject);",
            "parentId": null,
            "callbackType": null
        }]
    }
}